Metadata-Version: 2.1
Name: dr-cli
Version: 1.0.2
Summary: Scaffold your DRF projects faster⚡🚀
Home-page: https://github.com/Nyior/django-rest-cli
Author: Nyior Clement
Author-email: cnyior27@gmail.com
License: MIT
Project-URL: Bug Tracker, https://github.com/py-universe/django-rest-cli/issues
Project-URL: Source Code, https://github.com/py-universe/django-rest-cli
Keywords: python,rest,api,rest-framework,developer tool,cli
Platform: UNKNOWN
Classifier: Environment :: Web Environment
Classifier: Framework :: Django
Classifier: Framework :: Django :: 2.0
Classifier: Framework :: Django :: 3.0
Classifier: Intended Audience :: Developers
Classifier: License :: OSI Approved :: MIT License
Classifier: Operating System :: OS Independent
Classifier: Programming Language :: Python
Classifier: Programming Language :: Python :: 3
Classifier: Programming Language :: Python :: 3 :: Only
Classifier: Topic :: Internet
Classifier: Topic :: Internet :: WWW/HTTP
Requires-Python: >=3.8
License-File: LICENSE
Requires-Dist: Django (>=2.2)
Requires-Dist: PyInquirer (>=1.0.3)
Requires-Dist: black (>=22.3.0)
Requires-Dist: isort (>=5.10.1)
Requires-Dist: inflect (>=5.5.2)
Requires-Dist: colorama (>=0.4.4)
Requires-Dist: termcolor (>=1.1.0)
